libname/__init__.py
libname/hello.py
DMAHelloWorldpkg-0.0.1.dist-info/METADATA
DMAHelloWorldpkg-0.0.1.dist-info/WHEEL
DMAHelloWorldpkg-0.0.1.dist-info/top_level.txt
DMAHelloWorldpkg-0.0.1.dist-info/RECORD
