Metadata-Version: 2.1
Name: DMAHelloWorldpkg
Version: 0.0.1
Summary: Simple Hello World package
Home-page: UNKNOWN
Author: DMA
Author-email: <douniama72@gmail.com.com>
License: UNKNOWN
Keywords: python,helloworld
Platform: UNKNOWN
Classifier: Development Status :: 1 - Planning
Classifier: Intended Audience :: Developers
Classifier: Programming Language :: Python :: 3
Classifier: Operating System :: Unix
Classifier: Operating System :: MacOS :: MacOS X
Classifier: Operating System :: Microsoft :: Windows
